pytest_checkpoint/__init__.py
pytest_checkpoint/lap.py
pytest_checkpoint/logger.py
pytest_checkpoint/plugin.py
pytest_checkpoint/py.typed
pytest_checkpoint-0.1.3.dist-info/METADATA
pytest_checkpoint-0.1.3.dist-info/WHEEL
pytest_checkpoint-0.1.3.dist-info/licenses/LICENSE
pytest_checkpoint-0.1.3.dist-info/RECORD
