Metadata-Version: 2.4
Name: pytest-checkpoint
Version: 0.1.3
Summary: Restore a checkpoint in pytest
Author-email: Nick Grisafi <njgrisafi@gmail.com>
License-Expression: MIT
License-File: LICENSE
Classifier: Framework :: Pytest
Classifier: Intended Audience :: Developers
Classifier: License :: OSI Approved :: MIT License
Classifier: Programming Language :: Python :: 3 :: Only
Classifier: Programming Language :: Python :: 3.11
Classifier: Programming Language :: Python :: 3.12
Classifier: Programming Language :: Python :: 3.13
Classifier: Topic :: Software Development :: Testing
Classifier: Typing :: Typed
Requires-Python: >=3.11
Requires-Dist: pytest>=8.0.0
